motionrender/__init__.py
motionrender-1.0.0.dist-info/LICENSE
motionrender-1.0.0.dist-info/METADATA
motionrender-1.0.0.dist-info/WHEEL
motionrender-1.0.0.dist-info/top_level.txt
motionrender-1.0.0.dist-info/RECORD
